[
  {
    "section": 5,
    "section_name": "Air Brakes",
    "topic": "Governor cut-out pressure",
    "question": "At about what air tank pressure does the governor stop the compressor from pumping air (cut-out)?",
    "choices": [
      "100 psi",
      "125 psi",
      "150 psi",
      "60 psi"
    ],
    "answer_index": 1,
    "explanation": "When tank pressure rises to the cut-out level (around 125 psi), the governor stops the compressor from pumping air."
  },
  {
    "section": 5,
    "section_name": "Air Brakes",
    "topic": "Governor cut-in pressure",
    "question": "At about what tank pressure does the governor allow the compressor to start pumping again (cut-in)?",
    "choices": [
      "60 psi",
      "85 psi",
      "100 psi",
      "125 psi"
    ],
    "answer_index": 2,
    "explanation": "When tank pressure falls to the cut-in pressure (around 100 psi), the governor allows the compressor to start pumping again."
  },
  {
    "section": 5,
    "section_name": "Air Brakes",
    "topic": "Safety relief valve",
    "question": "At what pressure is the safety relief valve usually set to open?",
    "choices": [
      "125 psi",
      "135 psi",
      "150 psi",
      "175 psi"
    ],
    "answer_index": 2,
    "explanation": "The safety relief valve is usually set to open at 150 psi to protect the system from too much pressure."
  },
  {
    "section": 5,
    "section_name": "Air Brakes",
    "topic": "Low air pressure warning",
    "question": "A visible low air pressure warning signal must come on before tank pressure falls below what level?",
    "choices": [
      "45 psi",
      "60 psi",
      "80 psi",
      "100 psi"
    ],
    "answer_index": 1,
    "explanation": "A warning signal you can see must come on before the air pressure in the tanks falls below 60 psi."
  },
  {
    "section": 5,
    "section_name": "Air Brakes",
    "topic": "Wig wag",
    "question": "At what pressure does a wig wag device drop a mechanical arm into the driver's view?",
    "choices": [
      "Below 45 psi",
      "Below 60 psi",
      "Below 80 psi",
      "Below 100 psi"
    ],
    "answer_index": 1,
    "explanation": "The wig wag drops a mechanical arm into your view when system pressure drops below 60 psi."
  },
  {
    "section": 5,
    "section_name": "Air Brakes",
    "topic": "Spring brakes activation",
    "question": "Tractor and straight truck spring brakes come fully on when air pressure drops to what range?",
    "choices": [
      "10 to 20 psi",
      "20 to 45 psi",
      "45 to 60 psi",
      "60 to 85 psi"
    ],
    "answer_index": 1,
    "explanation": "Tractor and straight truck spring brakes will come fully on when air pressure drops to a range of 20 to 45 psi (typically 20 to 30 psi)."
  },
  {
    "section": 5,
    "section_name": "Air Brakes",
    "topic": "Automatic front wheel limiting valve",
    "question": "Automatic front wheel limiting valves stop reducing air to the front brakes when application pressure reaches about what level?",
    "choices": [
      "20 psi or more",
      "40 psi or more",
      "60 psi or more",
      "100 psi or more"
    ],
    "answer_index": 2,
    "explanation": "Automatic front wheel limiting valves reduce air to the front brakes except when the brakes are applied very hard (60 psi or more application pressure)."
  },
  {
    "section": 5,
    "section_name": "Air Brakes",
    "topic": "Dual system minimum pressure",
    "question": "Before driving a dual air system vehicle, the compressor should build a minimum of what pressure in both systems?",
    "choices": [
      "60 psi",
      "85 psi",
      "100 psi",
      "125 psi"
    ],
    "answer_index": 2,
    "explanation": "Allow time for the air compressor to build up a minimum of 100 psi pressure in both the primary and secondary systems before driving."
  },
  {
    "section": 5,
    "section_name": "Air Brakes",
    "topic": "Dual system warning",
    "question": "In a dual air brake system, the warning light and buzzer should come on before air pressure drops below what level in either system?",
    "choices": [
      "45 psi",
      "60 psi",
      "80 psi",
      "100 psi"
    ],
    "answer_index": 1,
    "explanation": "The warning light and buzzer should come on before the air pressure drops below 60 psi in either system."
  },
  {
    "section": 5,
    "section_name": "Air Brakes",
    "topic": "Slack adjuster check",
    "question": "When pulling on a slack adjuster, about how much movement indicates it probably needs adjustment?",
    "choices": [
      "More than about one quarter inch",
      "More than about one half inch",
      "More than about one inch",
      "More than about two inches"
    ],
    "answer_index": 2,
    "explanation": "If a slack adjuster moves more than about one inch where the push rod attaches, it probably needs adjustment."
  },
  {
    "section": 5,
    "section_name": "Air Brakes",
    "topic": "Brake drum cracks",
    "question": "Brake drums or discs must not have cracks longer than what fraction of the friction area width?",
    "choices": [
      "One quarter the width",
      "One third the width",
      "One half the width",
      "Two thirds the width"
    ],
    "answer_index": 2,
    "explanation": "Brake drums or discs must not have cracks longer than one half the width of the friction area."
  },
  {
    "section": 5,
    "section_name": "Air Brakes",
    "topic": "Leakage rate engine off, no brake",
    "question": "With the engine off and parking brake released, the air loss rate should be less than what for a single vehicle?",
    "choices": [
      "One psi in one minute",
      "Two psi in one minute",
      "Three psi in one minute",
      "Four psi in one minute"
    ],
    "answer_index": 1,
    "explanation": "The loss rate should be less than two psi in one minute for single vehicles and less than three psi for combination vehicles."
  },
  {
    "section": 5,
    "section_name": "Air Brakes",
    "topic": "Leakage rate with brake applied",
    "question": "With the foot brake fully applied for one minute, the air pressure should not drop more than what for a single vehicle?",
    "choices": [
      "Two psi in one minute",
      "Three psi in one minute",
      "Four psi in one minute",
      "Five psi in one minute"
    ],
    "answer_index": 1,
    "explanation": "With the foot brake fully applied, air pressure dropping more than three psi in one minute (single vehicle) means the air loss rate is too much."
  },
  {
    "section": 5,
    "section_name": "Air Brakes",
    "topic": "Spring brakes pop-out check",
    "question": "During the air brake check, the parking brake valve should pop out causing spring brakes to come on when pressure falls into what range?",
    "choices": [
      "10 to 20 psi",
      "20 to 45 psi",
      "45 to 60 psi",
      "60 to 85 psi"
    ],
    "answer_index": 1,
    "explanation": "The parking brake valve should close (pop out) and spring brakes come on when air pressure falls to the manufacturer's specification of 20 to 45 psi."
  },
  {
    "section": 5,
    "section_name": "Air Brakes",
    "topic": "Air pressure buildup rate",
    "question": "In dual air systems at operating rpm, pressure should build from 85 to 100 psi within how long?",
    "choices": [
      "30 seconds",
      "45 seconds",
      "60 seconds",
      "3 minutes"
    ],
    "answer_index": 1,
    "explanation": "In dual air systems, pressure should build from 85 to 100 psi within 45 seconds when the engine is at operating rpms."
  },
  {
    "section": 5,
    "section_name": "Air Brakes",
    "topic": "Stab braking",
    "question": "When using stab braking, when should you reapply the brakes after releasing them?",
    "choices": [
      "Immediately, without waiting",
      "As soon as the wheels start rolling again",
      "After holding the release for five seconds",
      "Only after the vehicle fully straightens"
    ],
    "answer_index": 1,
    "explanation": "In stab braking you release brakes when wheels lock up and reapply them fully as soon as the wheels start rolling again."
  },
  {
    "section": 5,
    "section_name": "Air Brakes",
    "topic": "Brake lag distance",
    "question": "About how much distance does air brake lag add at 55 mph on dry pavement?",
    "choices": [
      "About 12 feet",
      "About 32 feet",
      "About 60 feet",
      "About 100 feet"
    ],
    "answer_index": 1,
    "explanation": "The air brake lag distance at 55 mph on dry pavement adds about 32 feet."
  },
  {
    "section": 5,
    "section_name": "Air Brakes",
    "topic": "Downgrade braking technique",
    "question": "Using proper braking technique on a downgrade, when should you release the brakes after slowing?",
    "choices": [
      "When speed is reduced to about 5 mph below the safe speed",
      "When speed reaches the safe speed exactly",
      "After braking for ten seconds",
      "When speed is 10 mph above the safe speed"
    ],
    "answer_index": 0,
    "explanation": "Release the brakes when your speed has been reduced to approximately five mph below your safe speed."
  },
  {
    "section": 5,
    "section_name": "Air Brakes",
    "topic": "Spring Brake Activation",
    "question": "At what air pressure do spring brakes automatically come on?",
    "choices": [
      "60 psi",
      "45 psi or below",
      "80 psi",
      "100 psi"
    ],
    "answer_index": 1,
    "explanation": "Spring brakes automatically activate when air pressure drops to 20-45 psi (typically 20-30 psi)."
  },
  {
    "section": 5,
    "section_name": "Air Brakes",
    "topic": "Dual Air System",
    "question": "What is the minimum air pressure required in both systems before you can drive a dual air brake system vehicle?",
    "choices": [
      "50 psi in each",
      "80 psi in each",
      "100 psi in each",
      "120 psi in each"
    ],
    "answer_index": 2,
    "explanation": "You must have a minimum of 100 psi in both the primary and secondary air systems before driving."
  },
  {
    "section": 5,
    "section_name": "Air Brakes",
    "topic": "Alcohol Evaporator",
    "question": "What is the purpose of an alcohol evaporator in an air brake system?",
    "choices": [
      "To cool the air before braking",
      "To reduce ice buildup in the brake system in cold weather",
      "To increase braking power",
      "To filter out contaminants"
    ],
    "answer_index": 1,
    "explanation": "Alcohol evaporators are used in cold weather to reduce ice buildup inside the air brake system."
  },
  {
    "section": 5,
    "section_name": "Air Brakes",
    "topic": "Low Air Pressure Warning",
    "question": "Before what pressure level must the low air pressure warning light come on?",
    "choices": [
      "Before pressure drops below 100 psi",
      "Before pressure drops below 80 psi",
      "Before pressure drops below 60 psi",
      "At exactly 50 psi"
    ],
    "answer_index": 2,
    "explanation": "The low air pressure warning must come on before the pressure drops below 60 psi."
  },
  {
    "section": 5,
    "section_name": "Air Brakes",
    "topic": "Air Tank Drains",
    "question": "If your vehicle does not have automatic air tank drains, when should you drain the tanks?",
    "choices": [
      "Once per week",
      "At the end of each working day",
      "Only in winter",
      "Only when low air warning comes on"
    ],
    "answer_index": 1,
    "explanation": "If the vehicle does not have automatic drains, air tanks should be drained at the end of each working day to remove moisture and oil."
  },
  {
    "section": 5,
    "section_name": "Air Brakes",
    "topic": "Parking Brake Control",
    "question": "On newer air-brake vehicles, how do you apply spring parking brakes with the yellow knob?",
    "choices": [
      "Push in to apply",
      "Pull out to apply",
      "Turn left to apply",
      "Press the brake pedal twice"
    ],
    "answer_index": 1,
    "explanation": "On newer vehicles, the yellow diamond-shaped push-pull control is pulled out to apply parking brakes and pushed in to release."
  },
  {
    "section": 5,
    "section_name": "Air Brakes",
    "topic": "Spring Brakes Caution",
    "question": "Why should you avoid pressing the brake pedal when spring brakes are applied?",
    "choices": [
      "It drains fuel",
      "It can damage brakes from combined spring and air forces",
      "It disables ABS",
      "It turns off brake lights"
    ],
    "answer_index": 1,
    "explanation": "Pressing the pedal with spring brakes on can damage components due to combined spring force and air pressure."
  },
  {
    "section": 5,
    "section_name": "Air Brakes",
    "topic": "Brake Fade Cause",
    "question": "What is the main cause of brake fade on long downgrades?",
    "choices": [
      "Using engine braking too much",
      "Overheating from excessive service brake use",
      "Driving in low gear",
      "Too much tire pressure"
    ],
    "answer_index": 1,
    "explanation": "Brake fade is mainly caused by overheating from overusing service brakes instead of relying on proper gear and engine braking."
  },
  {
    "section": 5,
    "section_name": "Air Brakes",
    "topic": "Proper Downgrade Braking",
    "question": "After slowing about 5 mph below safe speed on a downgrade, what should you do next?",
    "choices": [
      "Keep heavy pressure on brakes",
      "Release brakes and let speed rise back to safe speed before reapplying",
      "Shift to higher gear",
      "Apply parking brake briefly"
    ],
    "answer_index": 1,
    "explanation": "Proper downgrade technique is to apply firm braking to reduce speed, release, then reapply when speed returns to the chosen safe speed."
  },
  {
    "section": 5,
    "section_name": "Air Brakes",
    "topic": "ABS Malfunction",
    "question": "If ABS malfunctions, what braking capability remains?",
    "choices": [
      "No brakes remain",
      "Only trailer brakes work",
      "Normal brakes still work, but ABS assist is lost",
      "Only parking brakes work"
    ],
    "answer_index": 2,
    "explanation": "ABS is an added safety system. If it fails, regular braking remains available, though wheel-lock control is reduced."
  },
  {
    "section": 5,
    "section_name": "Air Brakes",
    "topic": "Wet or Hot Parking Brakes",
    "question": "When should parking brakes be avoided temporarily?",
    "choices": [
      "Anytime in daylight",
      "When brakes are very hot or very wet in freezing temperatures",
      "Only on weekends",
      "When driving downhill"
    ],
    "answer_index": 1,
    "explanation": "Very hot brakes can be damaged if set immediately, and very wet brakes in freezing conditions can freeze. Use chocks when needed."
  },
  {
    "section": 5,
    "section_name": "Air Brakes",
    "topic": "Supply Pressure Gauge",
    "question": "What does the air supply pressure gauge tell you?",
    "choices": [
      "How hard you are pressing the brake pedal",
      "How much pressure is in the air tank(s)",
      "How much pressure is in each tire",
      "How hot the brake drums are"
    ],
    "answer_index": 1,
    "explanation": "Supply pressure gauges show the available air pressure in the reservoir tank(s)."
  },
  {
    "section": 5,
    "section_name": "Air Brakes",
    "topic": "ABS Equipment Check",
    "question": "How can you verify whether a vehicle is equipped with ABS?",
    "choices": [
      "Check tire sidewalls",
      "Check the certification label manufacturing date and ABS indicator lamps",
      "Listen for compressor noise",
      "Look for a blue parking brake knob"
    ],
    "answer_index": 1,
    "explanation": "The guide points to certification date and ABS malfunction lamps as key indicators of ABS equipment."
  },
  {
    "section": 5,
    "section_name": "Air Brakes",
    "topic": "Dual Air System Purpose",
    "question": "What is a dual air brake system?",
    "choices": [
      "Two pedals controlling front and rear brakes separately",
      "Two separate air systems sharing one set of brake controls for safety",
      "A system used only on trailers",
      "A backup hydraulic brake circuit"
    ],
    "answer_index": 1,
    "explanation": "A dual air system has primary and secondary circuits with separate tanks/lines for safety redundancy."
  },
  {
    "section": 5,
    "section_name": "Air Brakes",
    "topic": "Parking Brake Test",
    "question": "How do you test that the parking brake will hold?",
    "choices": [
      "Press and release pedal rapidly",
      "Set parking brake, then gently pull against it in a low gear",
      "Rev engine to governor cut-out",
      "Turn steering full left"
    ],
    "answer_index": 1,
    "explanation": "Section 5.3.3 says to apply the parking brake and gently pull against it in low gear to verify holding power."
  },
  {
    "section": 5,
    "section_name": "Air Brakes",
    "topic": "Service Brake Test",
    "question": "During final checks, how should service brakes be tested?",
    "choices": [
      "At highway speed only",
      "Move slowly (about 5 mph) and brake firmly, checking for pull or delayed stopping",
      "Only with trailer disconnected",
      "Only on steep downgrades"
    ],
    "answer_index": 1,
    "explanation": "Guide procedure calls for a low-speed, firm brake test to detect pull, unusual feel, or delay."
  },
  {
    "section": 5,
    "section_name": "Air Brakes",
    "topic": "Controlled Braking",
    "question": "What is controlled braking in an emergency?",
    "choices": [
      "Pump brakes lightly every second",
      "Brake as hard as possible without locking wheels, releasing if lockup occurs",
      "Use only engine brake",
      "Pull parking brake handle repeatedly"
    ],
    "answer_index": 1,
    "explanation": "Controlled braking uses strong brake pressure while avoiding wheel lock so steering control can be maintained."
  },
  {
    "section": 5,
    "section_name": "Air Brakes",
    "topic": "ABS Braking Method",
    "question": "When driving a tractor-trailer with ABS, what basic braking approach is recommended?",
    "choices": [
      "Brake differently depending on which unit has ABS",
      "Brake normally and monitor tractor/trailer stability",
      "Always stab-brake",
      "Use only trailer hand valve"
    ],
    "answer_index": 1,
    "explanation": "The guide says to brake the same way as usual, using only the force needed and monitoring stability."
  },
  {
    "section": 5,
    "section_name": "Air Brakes",
    "topic": "ABS Full-Brake Exception",
    "question": "When is full brake application in an emergency specifically allowed by the guide?",
    "choices": [
      "Any vehicle with at least one ABS axle",
      "Only if trailer ABS lamp is off",
      "If you always drive a straight truck or combination with working ABS on all axles",
      "Only below 25 mph"
    ],
    "answer_index": 2,
    "explanation": "Section 5.4.2 gives one exception: with working ABS on all axles (and that operating context), emergency full application is acceptable."
  },
  {
    "section": 5,
    "section_name": "Air Brakes",
    "topic": "Unattended Vehicle Safety",
    "question": "What should you do before leaving an air-brake vehicle unattended?",
    "choices": [
      "Leave it in neutral only",
      "Apply parking brakes or chock wheels",
      "Drain tanks completely first",
      "Disable ABS"
    ],
    "answer_index": 1,
    "explanation": "Never leave the vehicle unattended without applying parking brakes or using chocks to prevent rollaway."
  },
  {
    "section": 5,
    "section_name": "Air Brakes",
    "topic": "Stop Light Switch",
    "question": "What triggers the brake lights in an air brake system?",
    "choices": [
      "A mechanical linkage at each wheel",
      "An electric switch activated by air pressure",
      "The parking brake knob position only",
      "Compressor governor cut-out"
    ],
    "answer_index": 1,
    "explanation": "The stop-light switch is air-pressure operated and turns on brake lights when air brakes are applied."
  },
  {
    "section": 5,
    "section_name": "Air Brakes",
    "topic": "Application Pressure Gauge",
    "question": "If the application pressure gauge shows you need more pressure to hold the same speed, what is a likely problem?",
    "choices": [
      "Brakes may be fading or out of adjustment",
      "Air tanks are overfilled",
      "ABS is improving stopping power",
      "Compressor cut-out is too low"
    ],
    "answer_index": 0,
    "explanation": "Needing increasing application pressure for the same effect can indicate brake fade, adjustment issues, or leaks/mechanical faults."
  },
  {
    "section": 5,
    "section_name": "Air Brakes",
    "topic": "Pedal Pumping Risk",
    "question": "Why should you avoid pressing and releasing the brake pedal unnecessarily in an air brake vehicle?",
    "choices": [
      "It overheats only the front brakes",
      "It can use air faster than the compressor can replace it",
      "It disables the low-air warning",
      "It causes the parking brakes to release"
    ],
    "answer_index": 1,
    "explanation": "Unnecessary pedal cycling can deplete air pressure; if pressure gets too low, braking capability is reduced."
  },
  {
    "section": 5,
    "section_name": "Air Brakes",
    "topic": "Single-System Buildup Rate",
    "question": "For older single air systems, what buildup rate is typically required at idle?",
    "choices": [
      "50 to 90 psi within 3 minutes",
      "85 to 100 psi within 45 seconds",
      "60 to 120 psi within 2 minutes",
      "100 to 125 psi within 30 seconds"
    ],
    "answer_index": 0,
    "explanation": "For pre-1975 single systems, a typical requirement is pressure build from 50 to 90 psi within 3 minutes at 600-900 rpm idle."
  },
  {
    "section": 5,
    "section_name": "Air Brakes",
    "topic": "Modulating Control Valve",
    "question": "What is the purpose of a modulating spring-brake control valve?",
    "choices": [
      "To drain tanks automatically",
      "To apply spring brakes gradually for control if service brakes fail",
      "To increase compressor output",
      "To switch between ABS modes"
    ],
    "answer_index": 1,
    "explanation": "A modulating valve allows graduated spring-brake application, useful for controlling the vehicle during certain failures."
  },
  {
    "section": 5,
    "section_name": "Air Brakes",
    "topic": "Dual Parking Control Valves",
    "question": "On vehicles with dual parking control valves, why must emergency spring-brake release moves be planned carefully?",
    "choices": [
      "Because ABS is disabled during release",
      "Because the separate release tank has limited air and can be used only a few times",
      "Because front brakes do not work",
      "Because trailer brakes cannot be tested"
    ],
    "answer_index": 1,
    "explanation": "Some vehicles use a separate tank to release spring brakes temporarily; limited reserve means only a few releases are available."
  }
]